celery_salt/__init__.py
celery_salt/core/__init__.py
celery_salt/core/decorators.py
celery_salt/core/event_utils.py
celery_salt/core/events.py
celery_salt/core/exceptions.py
celery_salt/core/registry.py
celery_salt/core/versioning.py
celery_salt/django/__init__.py
celery_salt/django/celery.py
celery_salt/django/decorators.py
celery_salt/django/mixins.py
celery_salt/django/signals.py
celery_salt/integrations/__init__.py
celery_salt/integrations/client.py
celery_salt/integrations/dispatcher.py
celery_salt/integrations/producer.py
celery_salt/integrations/registry.py
celery_salt/logging/__init__.py
celery_salt/logging/formatters.py
celery_salt/logging/handlers.py
celery_salt/metrics/__init__.py
celery_salt/metrics/collectors.py
celery_salt/metrics/exporters.py
celery_salt/observability/__init__.py
celery_salt/observability/opentelemetry.py
celery_salt/utils/__init__.py
celery_salt/utils/error_handling.py
celery_salt/utils/json_encoder.py
celery_salt/utils/response_handler.py
celery_salt/version.py
celery_salt-1.4.5.dist-info/METADATA
celery_salt-1.4.5.dist-info/WHEEL
celery_salt-1.4.5.dist-info/licenses/LICENSE
celery_salt-1.4.5.dist-info/RECORD
