Metadata-Version: 2.4
Name: celery-salt
Version: 1.4.5
Summary: Event-driven architecture library for Python that extends Celery with event publishing/subscribing patterns
License: MIT
License-File: LICENSE
Keywords: celery,messaging,pydantic,django,events,pubsub,broadcast,microservices,event-driven,schema-registry
Author: David Sigley
Author-email: djsigley@gmail.com
Requires-Python: >=3.10,<4.0
Classifier: Development Status :: 4 - Beta
Classifier: Framework :: Celery
Classifier: Framework :: Django :: 4.0
Classifier: Intended Audience :: Developers
Classifier: License :: OSI Approved :: MIT License
Classifier: Programming Language :: Python :: 3
Classifier: Programming Language :: Python :: 3.10
Classifier: Programming Language :: Python :: 3.11
Classifier: Programming Language :: Python :: 3.12
Classifier: Programming Language :: Python :: 3.13
Classifier: Programming Language :: Python :: 3.14
Provides-Extra: all
Provides-Extra: django
Provides-Extra: opentelemetry
Provides-Extra: protobuf
Requires-Dist: celery (>=5.3.0,<6.0.0)
Requires-Dist: django (>=4.0.0,<5.0.0) ; extra == "django" or extra == "all"
Requires-Dist: kombu (>=5.3.0,<6.0.0)
Requires-Dist: opentelemetry-api (>=1.0.0,<2.0.0) ; extra == "opentelemetry" or extra == "all"
Requires-Dist: protobuf (>=4.0.0,<5.0.0) ; extra == "protobuf" or extra == "all"
Requires-Dist: pydantic (>=2.0.0,<3.0.0)
Project-URL: Documentation, https://github.com/sigularusrex/celery-salt
Project-URL: Homepage, https://github.com/sigularusrex/celery-salt
Project-URL: Repository, https://github.com/sigularusrex/celery-salt
